{
  "build": "0",
  "build_number": 0,
  "channel": "https://conda.anaconda.org/jmcmurray/noarch",
  "constrains": [],
  "depends": [
    "qutil"
  ],
  "extracted_package_dir": "/home/akizenko/anaconda3/pkgs/os-0.1.4-0",
  "features": "",
  "files": [
    "q/packages/os/init.q",
    "q/packages/os/os.q"
  ],
  "fn": "os-0.1.4-0.tar.bz2",
  "license": "MIT",
  "link": {
    "source": "/home/akizenko/anaconda3/pkgs/os-0.1.4-0",
    "type": 1
  },
  "md5": "a5d0a392aad9461cb1c7ad74d51f390b",
  "name": "os",
  "noarch": "generic",
  "package_tarball_full_path": "/home/akizenko/anaconda3/pkgs/os-0.1.4-0.tar.bz2",
  "package_type": "noarch_generic",
  "paths_data": {
    "paths": [
      {
        "_path": "q/packages/os/init.q",
        "path_type": "hardlink",
        "sha256": "2372a4d1bf75800b0a89303beb6a1605194ba56294c4aeda02a0dd87e0a5038b",
        "sha256_in_prefix": "2372a4d1bf75800b0a89303beb6a1605194ba56294c4aeda02a0dd87e0a5038b",
        "size_in_bytes": 28
      },
      {
        "_path": "q/packages/os/os.q",
        "path_type": "hardlink",
        "sha256": "b5c51370a3ce36060921faf769f195db1f6656c085c6cd90ee1b454c4752fa39",
        "sha256_in_prefix": "b5c51370a3ce36060921faf769f195db1f6656c085c6cd90ee1b454c4752fa39",
        "size_in_bytes": 1039
      }
    ],
    "paths_version": 1
  },
  "requested_spec": "os==0.1.4=0",
  "size": 3631,
  "subdir": "noarch",
  "timestamp": 1553031966574,
  "track_features": "",
  "url": "https://conda.anaconda.org/jmcmurray/noarch/os-0.1.4-0.tar.bz2",
  "version": "0.1.4"
}